[
	{ "s": "S", "p": [28, 29, 17, 34, 30, 38, 36, 35, 18, 27, 26, 23] },
	{ "s": "SAD", "p": [20] },
	{ "s": "SADDEST", "p": [37] },
	{ "s": "SAID", "p": [36, 30, 24, 16, 35, 22, 18] },
	{ "s": "SAIL", "p": [37] },
	{ "s": "SALDRÍA", "p": [41] },
	{ "s": "SALIDA", "p": [40] },
	{ "s": "SALIR", "p": [43] },
	{ "s": "SAME", "p": [38] },
	{ "s": "SANG", "p": [31] },
	{ "s": "SANGRE", "p": [43] },
	{ "s": "SAW", "p": [23, 21] },
	{ "s": "SAY", "p": [26, 23, 17, 35, 18, 15] },
	{ "s": "SAYING", "p": [15] },
	{ "s": "SAYS", "p": [30, 28] },
	{ "s": "SCENE", "p": [30] },
	{ "s": "SCHEMES", "p": [30] },
	{ "s": "SCOTT", "p": [35] },
	{ "s": "SCREEN", "p": [1] },
	{ "s": "SE", "p": [40, 41] },
	{ "s": "SECTION", "p": [35] },
	{ "s": "SEE", "p": [35, 15, 36, 28, 31, 26] },
	{ "s": "SEEM", "p": [16] },
	{ "s": "SEEMED", "p": [16] },
	{ "s": "SENTIMENTAL", "p": [17] },
	{ "s": "SET", "p": [37] },
	{ "s": "SEVEN", "p": [36] },
	{ "s": "SHALL", "p": [16] },
	{ "s": "SHARE", "p": [23] },
	{ "s": "SHARING", "p": [24] },
	{ "s": "SHARP", "p": [21] },
	{ "s": "SHE", "p": [30, 25, 35, 18, 37, 27, 22] },
	{ "s": "SHE'D", "p": [18] },
	{ "s": "SHE'S", "p": [30, 35] },
	{ "s": "SHEERAN", "p": [38] },
	{ "s": "SHINING", "p": [21] },
	{ "s": "SHONE", "p": [28] },
	{ "s": "SHORE", "p": [37] },
	{ "s": "SHOULD", "p": [29, 17] },
	{ "s": "SHOW", "p": [25] },
	{ "s": "SHOWED", "p": [30] },
	{ "s": "SHOWN", "p": [35] },
	{ "s": "SHOWS", "p": [25, 23] },
	{ "s": "SHY", "p": [23] },
	{ "s": "SI", "p": [41] },
	{ "s": "SIDE", "p": [30] },
	{ "s": "SIEMPRE", "p": [40] },
	{ "s": "SIGHT", "p": [24] },
	{ "s": "SIN", "p": [40] },
	{ "s": "SINATRA", "p": [24, 23] },
	{ "s": "SINCE", "p": [29, 24, 36] },
	{ "s": "SING", "p": [37] },
	{ "s": "SINGING", "p": [31] },
	{ "s": "SINGLE", "p": [38] },
	{ "s": "SIREN", "p": [21] },
	{ "s": "SIT", "p": [29] },
	{ "s": "SKY", "p": [35] },
	{ "s": "SLEEP", "p": [37, 36] },
	{ "s": "SLOW", "p": [34] },
	{ "s": "SMELL", "p": [30] },
	{ "s": "SMELLED", "p": [21] },
	{ "s": "SMILE", "p": [38, 24, 25, 15] },
	{ "s": "SMILE'S", "p": [38] },
	{ "s": "SMILED", "p": [18] },
	{ "s": "SMOKE", "p": [22] },
	{ "s": "SMOKEY", "p": [21] },
	{ "s": "SO", "p": [24, 35, 28, 20, 38, 27, 23, 36, 31, 30, 29, 26, 22, 16, 15, 1] },
	{ "s": "SOFT", "p": [34] },
	{ "s": "SOFTLY", "p": [31] },
	{ "s": "SOLA", "p": [42] },
	{ "s": "SOLO", "p": [26, 25, 42] },
	{ "s": "SOME", "p": [34, 33] },
	{ "s": "SOMEBODY", "p": [28, 35] },
	{ "s": "SOMEHOW", "p": [26] },
	{ "s": "SOMEONE", "p": [16, 15] },
	{ "s": "SOMETHING", "p": [25, 24] },
	{ "s": "SOMETIMES", "p": [15] },
	{ "s": "SOMEWHERE", "p": [25, 15] },
	{ "s": "SOMMERVILLE", "p": [28] },
	{ "s": "SON", "p": [30, 22, 41] },
	{ "s": "SON)BREAKING", "p": [30] },
	{ "s": "SONG", "p": [37, 31, 1, 42, 36, 35, 34, 24] },
	{ "s": "SONGS", "p": [47, 39, 32, 14, 2, 1, 37] },
	{ "s": "SONGWRITERS", "p": [30] },
	{ "s": "SONT", "p": [26] },
	{ "s": "SOON", "p": [30] },
	{ "s": "SORRY", "p": [16] },
	{ "s": "SOUL", "p": [27, 38] },
	{ "s": "SOY", "p": [42] },
	{ "s": "SPANISH", "p": [39] },
	{ "s": "SPELL", "p": [27] },
	{ "s": "SPINNING", "p": [35] },
	{ "s": "SPIT", "p": [23] },
	{ "s": "SPRINGS", "p": [21] },
	{ "s": "STAGE", "p": [16] },
	{ "s": "STAND", "p": [30, 19] },
	{ "s": "STANDARD", "p": [24] },
	{ "s": "STANDING", "p": [35, 16] },
	{ "s": "STARS", "p": [38] },
	{ "s": "START", "p": [19, 15] },
	{ "s": "STARTS", "p": [3] },
	{ "s": "STATE", "p": [23] },
	{ "s": "STEADY", "p": [37] },
	{ "s": "STEAL", "p": [20] },
	{ "s": "STEEL", "p": [21] },
	{ "s": "STEP", "p": [24, 23] },
	{ "s": "STICK", "p": [25] },
	{ "s": "STILETTOS", "p": [35] },
	{ "s": "STILL", "p": [38, 35, 18] },
	{ "s": "STOOD", "p": [31, 30, 23] },
	{ "s": "STOP", "p": [36] },
	{ "s": "STORY", "p": [27] },
	{ "s": "STRANGE", "p": [16] },
	{ "s": "STRANGER", "p": [31] },
	{ "s": "STRANGERS", "p": [24] },
	{ "s": "STRAY", "p": [16] },
	{ "s": "STREETS", "p": [21] },
	{ "s": "STRING", "p": [25, 3] },
	{ "s": "STRINGS", "p": [38, 24] },
	{ "s": "STRONG", "p": [34, 30] },
	{ "s": "STRUMMING", "p": [31] },
	{ "s": "STUDIO", "p": [42, 24] },
	{ "s": "STUPID", "p": [35] },
	{ "s": "STYLE", "p": [31, 25] },
	{ "s": "SUBE", "p": [40] },
	{ "s": "SUBO", "p": [40] },
	{ "s": "SUBSIDE", "p": [23] },
	{ "s": "SUCH", "p": [17] },
	{ "s": "SUERTE", "p": [40] },
	{ "s": "SUFRIDA", "p": [40] },
	{ "s": "SUGGESTIONS", "p": [1] },
	{ "s": "SUNNY", "p": [16] },
	{ "s": "SUNSHINE", "p": [15] },
	{ "s": "SURE", "p": [23] },
	{ "s": "SURROUNDS", "p": [33] },
	{ "s": "SURVIVES", "p": [37] },
	{ "s": "SWEEP", "p": [38] },
	{ "s": "SWEET", "p": [30, 16] },
	{ "s": "SWEETHEART", "p": [16] },
	{ "s": "SWORE", "p": [18] }
]