[
	{ "s": "ГАAAAA", "p": [60] },
	{ "s": "ГАAAAA-AAAЗ", "p": [60] },
	{ "s": "ГЕРОЙ", "p": [15] },
	{ "s": "ГИ", "p": [14] },
	{ "s": "ГЛАВА", "p": [15, 60] },
	{ "s": "ГНИЕ", "p": [11] },
	{ "s": "ГО", "p": [58, 60, 14, 59] },
	{ "s": "ГОВОРИТЕ", "p": [9] },
	{ "s": "ГОДИНИ", "p": [14, 5] },
	{ "s": "ГОЙКО", "p": [11] },
	{ "s": "ГОЛ", "p": [60] },
	{ "s": "ГОРЕЩИ", "p": [59] },
	{ "s": "ГРАД", "p": [12, 8] },
	{ "s": "ГРЕШЕН", "p": [9] },
	{ "s": "ГРЕШКА", "p": [61] },
	{ "s": "ГРЕШКИ", "p": [5] },
	{ "s": "ГРЕШНА", "p": [12] },
	{ "s": "ГРЕШНИ", "p": [15] },
	{ "s": "ГРЕШНО", "p": [8] },
	{ "s": "ГРУБ", "p": [58] },
	{ "s": "ГЪРДИ", "p": [58] },
	{ "s": "ГЪРЛА", "p": [59] }
]