[
	{ "s": "B", "p": [13, 9, 50, 25, 34, 11, 31, 26, 23, 41, 30, 29, 35, 5] },
	{ "s": "B------------------1", "p": [30] },
	{ "s": "B----1", "p": [5] },
	{ "s": "B----9--9---9---9---6-6--9---8---8---8", "p": [26] },
	{ "s": "B----9M---9M---9R---9R--6I---6I--9P--8P-8P--8PX3", "p": [26] },
	{ "s": "B7", "p": [40, 23, 24, 41, 50, 11, 31, 37, 29, 34] },
	{ "s": "B7-B-B7-B7", "p": [23] },
	{ "s": "BAAAD", "p": [29] },
	{ "s": "BABE", "p": [30] },
	{ "s": "BABY", "p": [34, 38, 28, 30, 36] },
	{ "s": "BABYLON", "p": [42] },
	{ "s": "BACK", "p": [37, 16] },
	{ "s": "BAJA", "p": [40] },
	{ "s": "BALDOZA", "p": [40] },
	{ "s": "BARE", "p": [16] },
	{ "s": "BB", "p": [15, 11, 6] },
	{ "s": "BE", "p": [34, 33, 20, 30, 24, 28, 27, 38, 22, 19, 18, 17] },
	{ "s": "BEATIN", "p": [20] },
	{ "s": "BEATING", "p": [38] },
	{ "s": "BEATLES", "p": [26, 25] },
	{ "s": "BEATS", "p": [21] },
	{ "s": "BEAUTY", "p": [30] },
	{ "s": "BECAUSE", "p": [29] },
	{ "s": "BECOMES", "p": [30] },
	{ "s": "BEEN", "p": [24, 36, 34, 29, 15] },
	{ "s": "BEFORE", "p": [24, 22, 38] },
	{ "s": "BEG", "p": [20] },
	{ "s": "BEGGIN", "p": [20] },
	{ "s": "BEING", "p": [30] },
	{ "s": "BELIEVE", "p": [34, 25, 18] },
	{ "s": "BELLE", "p": [26] },
	{ "s": "BELONGS", "p": [29, 27] },
	{ "s": "BEST", "p": [22] },
	{ "s": "BET", "p": [35] },
	{ "s": "BETTER", "p": [36, 35] },
	{ "s": "BIEN", "p": [26] },
	{ "s": "BIG", "p": [35, 21] },
	{ "s": "BIGGEST", "p": [37] },
	{ "s": "BILLIE", "p": [30] },
	{ "s": "BIRD", "p": [36] },
	{ "s": "BIT", "p": [23] },
	{ "s": "BLACK", "p": [35] },
	{ "s": "BLACKEST", "p": [18] },
	{ "s": "BLIND", "p": [28] },
	{ "s": "BLOWS", "p": [23] },
	{ "s": "BLUE", "p": [20] },
	{ "s": "BLUES", "p": [37, 36] },
	{ "s": "BLUEST", "p": [37] },
	{ "s": "BM", "p": [6, 37, 28, 11, 22, 38, 23, 5, 42] },
	{ "s": "BM7", "p": [50] },
	{ "s": "BOLA", "p": [41] },
	{ "s": "BOLIVIANO", "p": [42] },
	{ "s": "BOTTLES", "p": [35] },
	{ "s": "BOUT", "p": [34, 38] },
	{ "s": "BOY", "p": [36] },
	{ "s": "BRAIN", "p": [28] },
	{ "s": "BRDG", "p": [30] },
	{ "s": "BREAKING", "p": [30] },
	{ "s": "BREATHE", "p": [28] },
	{ "s": "BREEZE", "p": [21] },
	{ "s": "BRIDGE", "p": [35, 33, 38, 29, 25, 23, 22, 21, 19] },
	{ "s": "BRIGHTER", "p": [16] },
	{ "s": "BRING", "p": [28, 16] },
	{ "s": "BROKEN", "p": [35] },
	{ "s": "BUENO", "p": [40] },
	{ "s": "BULGARIAN", "p": [47, 44, 2, 1] },
	{ "s": "BURLAR", "p": [42] },
	{ "s": "BURNING", "p": [27, 18] },
	{ "s": "BUSCAR", "p": [40] },
	{ "s": "BUT", "p": [30, 35, 36, 38, 28, 23, 22, 20, 18, 17, 31, 27, 19, 16, 15] },
	{ "s": "BUTTON", "p": [1] },
	{ "s": "BY", "p": [21, 1, 27, 31, 30, 26, 18, 17, 15] },
	{ "s": "BYWAY", "p": [23] }
]